{"STATUS":[{"STATUS":"S","When":1588062621,"Code":70,"Msg":"BMMiner stats","Description":"bmminer 1.0.0"}],"STATS":[{"BMMiner":"2.0.0","Miner":"26.0.1.3","CompileTime":"Sat Aug 10 12:32:13 PST 2019","Type":"Antminer T9 Hiveon"}{"STATS":0,"ID":"BC50","Elapsed":79637,"Calls":0,"Wait":0.000000,"Max":0.000000,"Min":99999999.000000,"GHS 5s":"7817.830","GHS av":7781.84,"miner_count":9,"frequency":"425","fan_num":2,"fan1":0,"fan2":0,"fan3":0,"fan4":0,"fan5":3120,"fan6":4680,"fan7":0,"fan8":0,"temp_num":9,"temp1":0,"temp2":73,"temp3":67,"temp4":60,"temp5":0,"temp6":0,"temp7":0,"temp8":0,"temp9":73,"temp10":73,"temp11":67,"temp12":67,"temp13":60,"temp14":60,"temp15":0,"temp16":0,"temp2_1":0,"temp2_2":79,"temp2_3":72,"temp2_4":71,"temp2_5":0,"temp2_6":0,"temp2_7":0,"temp2_8":0,"temp2_9":79,"temp2_10":79,"temp2_11":72,"temp2_12":72,"temp2_13":71,"temp2_14":71,"temp2_15":0,"temp2_16":0,"temp3_1":0,"temp3_2":-26,"temp3_3":0,"temp3_4":0,"temp3_5":0,"temp3_6":0,"temp3_7":0,"temp3_8":0,"temp3_9":-26,"temp3_10":-26,"temp3_11":0,"temp3_12":0,"temp3_13":0,"temp3_14":0,"temp3_15":0,"temp3_16":0,"freq_avg1":0.00,"freq_avg2":425.00,"freq_avg3":425.00,"freq_avg4":425.00,"freq_avg5":0.00,"freq_avg6":0.00,"freq_avg7":0.00,"freq_avg8":0.00,"freq_avg9":425.00,"freq_avg10":425.00,"freq_avg11":425.00,"freq_avg12":425.00,"freq_avg13":425.00,"freq_avg14":425.00,"freq_avg15":0.00,"freq_avg16":0.00,"total_rateideal":7848.90,"total_freqavg":425.00,"total_acn":162,"total_rate":7817.82,"chain_rateideal1":0.00,"chain_rateideal2":872.10,"chain_rateideal3":872.10,"chain_rateideal4":872.10,"chain_rateideal5":0.00,"chain_rateideal6":0.00,"chain_rateideal7":0.00,"chain_rateideal8":0.00,"chain_rateideal9":872.10,"chain_rateideal10":872.10,"chain_rateideal11":872.10,"chain_rateideal12":872.10,"chain_rateideal13":872.10,"chain_rateideal14":872.10,"chain_rateideal15":0.00,"chain_rateideal16":0.00,"temp_max":79,"Device Hardware%":0.0000,"no_matching_work":54,"chain_acn1":0,"chain_acn2":18,"chain_acn3":18,"chain_acn4":18,"chain_acn5":0,"chain_acn6":0,"chain_acn7":0,"chain_acn8":0,"chain_acn9":18,"chain_acn10":18,"chain_acn11":18,"chain_acn12":18,"chain_acn13":18,"chain_acn14":18,"chain_acn15":0,"chain_acn16":0,"chain_acs1":"","chain_acs2":" oooooooo oooooooo oo","chain_acs3":" oooooooo oooooooo oo","chain_acs4":" oooooooo oooooooo oo","chain_acs5":"","chain_acs6":"","chain_acs7":"","chain_acs8":"","chain_acs9":" oooooooo oooooooo oo","chain_acs10":" oooooooo oooooooo oo","chain_acs11":" oooooooo oooooooo oo","chain_acs12":" oooooooo oooooooo oo","chain_acs13":" oooooooo oooooooo oo","chain_acs14":" oooooooo oooooooo oo","chain_acs15":"","chain_acs16":"","chain_hw1":0,"chain_hw2":3,"chain_hw3":4,"chain_hw4":1,"chain_hw5":0,"chain_hw6":0,"chain_hw7":0,"chain_hw8":0,"chain_hw9":6,"chain_hw10":6,"chain_hw11":3,"chain_hw12":2,"chain_hw13":22,"chain_hw14":2,"chain_hw15":0,"chain_hw16":0,"chain_rate1":0.00,"chain_rate2":884.09,"chain_rate3":858.83,"chain_rate4":863.62,"chain_rate5":0.00,"chain_rate6":0.00,"chain_rate7":0.00,"chain_rate8":0.00,"chain_rate9":880.94,"chain_rate10":872.75,"chain_rate11":866.96,"chain_rate12":870.49,"chain_rate13":863.49,"chain_rate14":856.66,"chain_rate15":0.00,"chain_rate16":0.00,"chain_xtime2":"{X0=1,X2=1,X8=1,X12=1}","chain_xtime3":"{X0=1,X4=1,X8=1,X9=1,X10=2}","chain_xtime4":"{X1=1,X2=1,X6=2,X8=1,X9=1,X10=1,X12=1,X14=1,X17=2}","chain_xtime9":"{X1=1,X6=1,X7=1,X10=1,X11=1}","chain_xtime10":"{X4=1,X7=1,X15=1,X17=1}","chain_xtime11":"{X0=1,X3=1,X5=1,X9=1,X13=1,X15=1}","chain_xtime12":"{X3=1,X6=1,X9=1}","chain_xtime13":"{X0=1,X2=1,X5=1,X7=1,X9=2,X14=1,X16=1}","chain_xtime14":"{X3=1,X10=1,X16=1}","chain_offside_2":"0","chain_offside_3":"0","chain_offside_4":"0","chain_offside_9":"0","chain_offside_10":"0","chain_offside_11":"0","chain_offside_12":"0","chain_offside_13":"0","chain_offside_14":"0","chain_opencore_2":"0","chain_opencore_3":"0","chain_opencore_4":"0","chain_opencore_9":"0","chain_opencore_10":"0","chain_opencore_11":"0","chain_opencore_12":"0","chain_opencore_13":"0","chain_opencore_14":"0","miner_version":"26.0.1.3","chain_power1":0.00,"chain_power2":92.51,"chain_power3":92.51,"chain_power4":92.51,"chain_power5":0.00,"chain_power6":0.00,"chain_power7":0.00,"chain_power8":0.00,"chain_power9":92.51,"chain_power10":92.51,"chain_power11":92.51,"chain_power12":92.51,"chain_power13":92.51,"chain_power14":92.51,"chain_power15":0.00,"chain_power16":0.00,"chain_power":"832.59 (AB)"}],"id":1}